quickspirit/__init__.py
quickspirit/http_async_client.py
quickspirit/http_async_downloader.py
quickspirit/http_errors.py
quickspirit/models.py
quickspirit-2.1.1.dist-info/LICENSE
quickspirit-2.1.1.dist-info/METADATA
quickspirit-2.1.1.dist-info/WHEEL
quickspirit-2.1.1.dist-info/RECORD
