Metadata-Version: 2.3
Name: quickspirit
Version: 2.1.1
Summary: Fast, Async Network & File Downloader Client In Python
Home-page: https://github.com/DroidZed/QuickSpirit-Async
License: GPL-3.0-or-later
Keywords: api,speed,fast,library,networking
Author: DroidZed
Author-email: 41507665+DroidZed@users.noreply.github.com
Requires-Python: >=3.9
Classifier: Intended Audience :: Developers
Classifier: License :: OSI Approved :: GNU General Public License v3 (GPLv3)
Classifier: License :: OSI Approved :: GNU General Public License v3 or later (GPLv3+)
Classifier: Operating System :: OS Independent
Classifier: Programming Language :: Python
Classifier: Programming Language :: Python :: 3
Classifier: Programming Language :: Python :: 3.9
Classifier: Programming Language :: Python :: 3.10
Classifier: Programming Language :: Python :: 3.11
Classifier: Programming Language :: Python :: 3.12
Classifier: Programming Language :: Python :: 3.13
Requires-Dist: aiofiles (>=24.1.0)
Requires-Dist: httpx (>=0.27.0)
Project-URL: Repository, https://github.com/DroidZed/QuickSpirit-Async
